README.md
setup.py
tap_outbrain/__init__.py
tap_outbrain/schemas.py
tap_outbrain.egg-info/PKG-INFO
tap_outbrain.egg-info/SOURCES.txt
tap_outbrain.egg-info/dependency_links.txt
tap_outbrain.egg-info/entry_points.txt
tap_outbrain.egg-info/requires.txt
tap_outbrain.egg-info/top_level.txt