Metadata-Version: 1.1
Name: tap-outbrain
Version: 0.1.10
Summary: Singer.io tap for extracting data from the Outbrain API
Home-page: http://singer.io
Author: Fishtown Analytics
Author-email: UNKNOWN
License: UNKNOWN
Platform: UNKNOWN
Classifier: Programming Language :: Python :: 3 :: Only
